{
    "Ar36": {
        "error": 0.0017238136206215013,
        "error_type": "SEM",
        "filter_outliers_dict": {
            "filter_outliers": true,
            "iterations": 1,
            "std_devs": 3,
            "use_iqr_filtering": false,
            "use_standard_deviation_filtering": false
        },
        "fit": "linear",
        "fn": 339,
        "include_baseline_error": false,
        "n": 340,
        "outlier_excluded": [
            25
        ],
        "reviewed": true,
        "user_excluded": [],
        "value": 1.3863557447952157
    },
    "Ar37": {
        "error": 0.01492008056951377,
        "error_type": "SEM",
        "filter_outliers_dict": {
            "filter_outliers": true,
            "iterations": 1,
            "std_devs": 3,
            "use_iqr_filtering": false,
            "use_standard_deviation_filtering": false
        },
        "fit": "linear",
        "fn": 338,
        "include_baseline_error": false,
        "n": 340,
        "outlier_excluded": [
            89,
            125
        ],
        "reviewed": true,
        "user_excluded": [],
        "value": 0.5399782400584383
    },
    "Ar38": {
        "error": 0.005870352864787617,
        "error_type": "SEM",
        "filter_outliers_dict": {
            "filter_outliers": true,
            "iterations": 1,
            "std_devs": 3,
            "use_iqr_filtering": false,
            "use_standard_deviation_filtering": false
        },
        "fit": "linear",
        "fn": 339,
        "include_baseline_error": false,
        "n": 340,
        "outlier_excluded": [
            267
        ],
        "reviewed": true,
        "user_excluded": [],
        "value": 4.953978649077921
    },
    "Ar39": {
        "error": 0.01060924352738824,
        "error_type": "SEM",
        "filter_outliers_dict": {
            "filter_outliers": true,
            "iterations": 1,
            "std_devs": 3,
            "use_iqr_filtering": false,
            "use_standard_deviation_filtering": false
        },
        "fit": "linear",
        "fn": 340,
        "include_baseline_error": false,
        "n": 340,
        "outlier_excluded": [],
        "reviewed": true,
        "user_excluded": [],
        "value": 31.02153763895
    },
    "Ar40": {
        "error": 0.05752906173168875,
        "error_type": "SEM",
        "filter_outliers_dict": {
            "filter_outliers": true,
            "iterations": 1,
            "std_devs": 3,
            "use_iqr_filtering": false,
            "use_standard_deviation_filtering": false
        },
        "fit": "parabolic",
        "fn": 336,
        "include_baseline_error": false,
        "n": 340,
        "outlier_excluded": [
            224,
            225,
            66,
            226
        ],
        "reviewed": true,
        "user_excluded": [],
        "value": 473.9807103630209
    }
}