{
    "Ar36": {
        "error": 0.003884069032077594,
        "error_type": "SEM",
        "filter_outliers_dict": {
            "filter_outliers": true,
            "iterations": 1,
            "std_devs": 3,
            "use_iqr_filtering": false,
            "use_standard_deviation_filtering": false
        },
        "fit": "parabolic",
        "fn": 339,
        "include_baseline_error": false,
        "n": 340,
        "outlier_excluded": [
            50
        ],
        "reviewed": true,
        "user_excluded": [],
        "value": 2.4163947670599573
    },
    "Ar37": {
        "error": 0.01633878438013988,
        "error_type": "SEM",
        "filter_outliers_dict": {
            "filter_outliers": true,
            "iterations": 1,
            "std_devs": 3,
            "use_iqr_filtering": false,
            "use_standard_deviation_filtering": false
        },
        "fit": "linear",
        "fn": 339,
        "include_baseline_error": false,
        "n": 340,
        "outlier_excluded": [
            336
        ],
        "reviewed": true,
        "user_excluded": [],
        "value": 1.3181867241577023
    },
    "Ar38": {
        "error": 0.006388672485498085,
        "error_type": "SEM",
        "filter_outliers_dict": {
            "filter_outliers": true,
            "iterations": 1,
            "std_devs": 3,
            "use_iqr_filtering": false,
            "use_standard_deviation_filtering": false
        },
        "fit": "linear",
        "fn": 340,
        "include_baseline_error": false,
        "n": 340,
        "outlier_excluded": [],
        "reviewed": true,
        "user_excluded": [],
        "value": 9.402905817402733
    },
    "Ar39": {
        "error": 0.019540603729719344,
        "error_type": "SEM",
        "filter_outliers_dict": {
            "filter_outliers": true,
            "iterations": 1,
            "std_devs": 3,
            "use_iqr_filtering": false,
            "use_standard_deviation_filtering": false
        },
        "fit": "parabolic",
        "fn": 336,
        "include_baseline_error": false,
        "n": 340,
        "outlier_excluded": [
            8,
            219,
            84,
            112
        ],
        "reviewed": true,
        "user_excluded": [],
        "value": 51.08918996303656
    },
    "Ar40": {
        "error": 0.0861308679999085,
        "error_type": "SEM",
        "filter_outliers_dict": {
            "filter_outliers": true,
            "iterations": 1,
            "std_devs": 3,
            "use_iqr_filtering": false,
            "use_standard_deviation_filtering": false
        },
        "fit": "parabolic",
        "fn": 336,
        "include_baseline_error": false,
        "n": 340,
        "outlier_excluded": [
            220,
            219,
            68,
            251
        ],
        "reviewed": true,
        "user_excluded": [],
        "value": 821.0069763969058
    }
}